kitchen_sink/__init__.py
python_kitchen_sink-0.0.0a0.dist-info/WHEEL
python_kitchen_sink-0.0.0a0.dist-info/METADATA
python_kitchen_sink-0.0.0a0.dist-info/RECORD
