Metadata-Version: 2.1
Name: python-kitchen-sink
Version: 0.0.0a0
Summary: Everything but the kitchen sink
Home-page: https://github.com/munro/python-kitchen-sink
License: MIT
Author: Ryan Munro
Author-email: 500774+munro@users.noreply.github.com
Requires-Python: >=3.10,<4.0
Classifier: License :: OSI Approved :: MIT License
Classifier: Programming Language :: Python :: 3
Classifier: Programming Language :: Python :: 3.10
Project-URL: Documentation, https://kitchen-sink.readthedocs.io/en/latest/
Project-URL: Repository, https://github.com/munro/python-kitchen-sink
